PySmeQcd/__init__.py
PySmeQcd/settings.py
PySmeQcd/oneloop/__init__.py
PySmeQcd/oneloop/ghost.py
PySmeQcd/oneloop/gluon.py
PySmeQcd/oneloop/oneloop_settings.py
PySmeQcd/oneloop/quark.py
PySmeQcd-1.1.0a0.dist-info/LICENSE
PySmeQcd-1.1.0a0.dist-info/METADATA
PySmeQcd-1.1.0a0.dist-info/WHEEL
PySmeQcd-1.1.0a0.dist-info/top_level.txt
PySmeQcd-1.1.0a0.dist-info/RECORD
