Metadata-Version: 2.1
Name: PySmeQcd
Version: 1.1.0a0
Summary: A Python library for the Screened Massive Expansion of QCD
Home-page: https://github.com/GComitini/PySmeQcd
Author: Giorgio Comitini
Author-email: giorgio.comitini@dfa.unict.it
License: UNKNOWN
Project-URL: Source, https://github.com/GComitini/PySmeQcd/
Project-URL: Documentation, https://pysmeqcd.readthedocs.io
Project-URL: Bug Tracker, https://github.com/GComitini/PySmeQcd/issues
Keywords: theoretical physics QCD QFT quantum chromodynamics field theory screened massive expansion gluon quark propagator development
Platform: UNKNOWN
Classifier: Programming Language :: Python :: 3
Classifier: License :: OSI Approved :: GNU General Public License v3 or later (GPLv3+)
Classifier: Operating System :: OS Independent
Classifier: Development Status :: 3 - Alpha
Classifier: Intended Audience :: Science/Research
Classifier: Topic :: Scientific/Engineering :: Physics
Requires-Python: >=3
License-File: LICENSE
Requires-Dist: matplotlib
Requires-Dist: numpy
Requires-Dist: scipy
